Workbook

Sheet Hypothèses
A1: Plombier artisan / TPE — Hypothèses
A2: Métier : plombier indépendant ou TPE | CA cible ≈ 200 k€ en Année 1, sur 3 ans | Cellules bleues = modifiables
A4: Chiffre d'affaires annuel HT — Année 1 (€) | C4: 200000
A5: Taux de TVA moyen sur les ventes (%) | C5: 0.12
A6: Taux de TVA moyen sur les achats (%) | C6: 0.2
A7: Trésorerie disponible au 1er janvier Année 1 (€) | C7: 8000
A8: Cotisations sociales du dirigeant (TNS) — par trimestre, Année 1 (€) | C8: 2000
A9: Remboursement emprunt véhicule/outillage — mensualité fixe (€) | C9: 280
A10: Part du CA encaissée le mois même (cash/CB/chèque à la prestation) (%) | C10: 1
A11: Part du CA encaissée à M-1 (%) | C11: 0
A12: Part du CA encaissée à M-2 (%) | C12: 0 | D12: Contrôle (doit = 100%) | E12: =C10+C11+C12
A13: Taux de croissance du CA — par an (%) | C13: 0.025
A14: Taux d'inflation des prix d'achat — par an (%) | C14: 0.03
A16: Mois (motif répété chaque année) | C16: Jan | D16: Fév | E16: Mar | F16: Avr | G16: Mai | H16: Jui | I16: Jui | J16: Aoû | K16: Sep | L16: Oct | M16: Nov | N16: Déc
A17: Indice de saisonnalité (1 = mois moyen) | C17: 1.15 | D17: 1.05 | E17: 1 | F17: 0.95 | G17: 0.9 | H17: 0.9 | I17: 0.85 | J17: 0.7 | K17: 1 | L17: 1.1 | M17: 1.15 | N17: 1.05
A18: Poids du mois dans l'année (%, normalisé) | C18: =C17/SUM($C$17:$N$17) | D18: =D17/SUM($C$17:$N$17) | E18: =E17/SUM($C$17:$N$17) | F18: =F17/SUM($C$17:$N$17) | G18: =G17/SUM($C$17:$N$17) | H18: =H17/SUM($C$17:$N$17) | I18: =I17/SUM($C$17:$N$17) | J18: =J17/SUM($C$17:$N$17) | ... N18: =N17/SUM($C$17:$N$17)
A20: Note saisonnalité : pics en hiver (pannes chauffage, gel des canalisations en janvier/novembre/décembre) et à la rentrée (mise en route chauffage en octobre) ; creux en été (-30% en août). Motif répété chaque année.
A21: Note évolution 3 ans : le CA croît de 2,5%/an, les prix d'achat de 3%/an. Les lignes cuivre, carburant et électricité utilisent une simulation de fluctuation mensuelle réaliste (pas une inflation lissée).
A23: Légende
A24: ■ | B24: Saisie modifiable (hypothèse)
A25: ■ | B25: Formule calculée automatiquement
A26: ■ | B26: Lien vers un autre onglet
A27: ■ | B27: Prix indicatif en attente de connexion à une API de prix de marché (voir onglet Benchmarks & sources)

Sheet Revenus
A1: Plombier — Revenus mensuels (3 ans)
A2: Répartition du CA par type d'intervention × saisonnalité × croissance annuelle
C3: ANNÉE 1 | O3: ANNÉE 2 | AA3: ANNÉE 3
A4: Source de revenus | B4: % du CA annuel | C4: Jan A1 | D4: Fév A1 | E4: Mar A1 | F4: Avr A1 | G4: Mai A1 | H4: Jui A1 | I4: Jui A1 | J4: Aoû A1 | K4: Sep A1 | L4: Oct A1 | M4: Nov A1 | N4: Déc A1 | O4: Jan A2 | P4: Fév A2 | Q4: Mar A2 | R4: Avr A2 | S4: Mai A2 | T4: Jui A2 | U4: Jui A2 | V4: Aoû A2 | W4: Sep A2 | X4: Oct A2 | Y4: Nov A2 | Z4: Déc A2 | AA4: Jan A3 | AB4: Fév A3 | AC4: Mar A3 | AD4: Avr A3 | AE4: Mai A3 | AF4: Jui A3 | AG4: Jui A3 | AH4: Aoû A3 | AI4: Sep A3 | AJ4: Oct A3 | AK4: Nov A3 | AL4: Déc A3 | AM4: Total A1 | AN4: Total A2 | AO4: Total A3 | AP4: Total 3 ans
A5: Dépannage urgence (fuites, pannes) | B5: 0.3 | C5: =Hypothèses!$C$4*$B5*Hypothèses!C$18*(1+Hypothèses!$C$13)^0 | D5: =Hypothèses!$C$4*$B5*Hypothèses!D$18*(1+Hypothèses!$C$13)^0 | E5: =Hypothèses!$C$4*$B5*Hypothèses!E$18*(1+Hypothèses!$C$13)^0 | F5: =Hypothèses!$C$4*$B5*Hypothèses!F$18*(1+Hypothèses!$C$13)^0 | G5: =Hypothèses!$C$4*$B5*Hypothèses!G$18*(1+Hypothèses!$C$13)^0 | H5: =Hypothèses!$C$4*$B5*Hypothèses!H$18*(1+Hypothèses!$C$13)^0 | I5: =Hypothèses!$C$4*$B5*Hypothèses!I$18*(1+Hypothèses!$C$13)^0 | J5: =Hypothèses!$C$4*$B5*Hypothèses!J$18*(1+Hypothèses!$C$13)^0 | ... N5: =Hypothèses!$C$4*$B5*Hypothèses!N$18*(1+Hypothèses!$C$13)^0 | O5: =Hypothèses!$C$4*$B5*Hypothèses!C$18*(1+Hypothèses!$C$13)^1 | P5: =Hypothèses!$C$4*$B5*Hypothèses!D$18*(1+Hypothèses!$C$13)^1 | Q5: =Hypothèses!$C$4*$B5*Hypothèses!E$18*(1+Hypothèses!$C$13)^1 | R5: =Hypothèses!$C$4*$B5*Hypothèses!F$18*(1+Hypothèses!$C$13)^1 | S5: =Hypothèses!$C$4*$B5*Hypothèses!G$18*(1+Hypothèses!$C$13)^1 | T5: =Hypothèses!$C$4*$B5*Hypothèses!H$18*(1+Hypothèses!$C$13)^1 | U5: =Hypothèses!$C$4*$B5*Hypothèses!I$18*(1+Hypothèses!$C$13)^1 | V5: =Hypothèses!$C$4*$B5*Hypothèses!J$18*(1+Hypothèses!$C$13)^1 | ... Z5: =Hypothèses!$C$4*$B5*Hypothèses!N$18*(1+Hypothèses!$C$13)^1 | AA5: =Hypothèses!$C$4*$B5*Hypothèses!C$18*(1+Hypothèses!$C$13)^2 | AB5: =Hypothèses!$C$4*$B5*Hypothèses!D$18*(1+Hypothèses!$C$13)^2 | AC5: =Hypothèses!$C$4*$B5*Hypothèses!E$18*(1+Hypothèses!$C$13)^2 | AD5: =Hypothèses!$C$4*$B5*Hypothèses!F$18*(1+Hypothèses!$C$13)^2 | AE5: =Hypothèses!$C$4*$B5*Hypothèses!G$18*(1+Hypothèses!$C$13)^2 | AF5: =Hypothèses!$C$4*$B5*Hypothèses!H$18*(1+Hypothèses!$C$13)^2 | AG5: =Hypothèses!$C$4*$B5*Hypothèses!I$18*(1+Hypothèses!$C$13)^2 | AH5: =Hypothèses!$C$4*$B5*Hypothèses!J$18*(1+Hypothèses!$C$13)^2 | ... AL5: =Hypothèses!$C$4*$B5*Hypothèses!N$18*(1+Hypothèses!$C$13)^2 | AM5: =SUM(C5:N5) | AN5: =SUM(O5:Z5) | AO5: =SUM(AA5:AL5) | AP5: =SUM(AM5:AO5)
A6: Installation neuve (sanitaire, chauffage) | B6: 0.25 | C6: =Hypothèses!$C$4*$B6*Hypothèses!C$18*(1+Hypothèses!$C$13)^0 | D6: =Hypothèses!$C$4*$B6*Hypothèses!D$18*(1+Hypothèses!$C$13)^0 | E6: =Hypothèses!$C$4*$B6*Hypothèses!E$18*(1+Hypothèses!$C$13)^0 | F6: =Hypothèses!$C$4*$B6*Hypothèses!F$18*(1+Hypothèses!$C$13)^0 | G6: =Hypothèses!$C$4*$B6*Hypothèses!G$18*(1+Hypothèses!$C$13)^0 | H6: =Hypothèses!$C$4*$B6*Hypothèses!H$18*(1+Hypothèses!$C$13)^0 | I6: =Hypothèses!$C$4*$B6*Hypothèses!I$18*(1+Hypothèses!$C$13)^0 | J6: =Hypothèses!$C$4*$B6*Hypothèses!J$18*(1+Hypothèses!$C$13)^0 | ... N6: =Hypothèses!$C$4*$B6*Hypothèses!N$18*(1+Hypothèses!$C$13)^0 | O6: =Hypothèses!$C$4*$B6*Hypothèses!C$18*(1+Hypothèses!$C$13)^1 | P6: =Hypothèses!$C$4*$B6*Hypothèses!D$18*(1+Hypothèses!$C$13)^1 | Q6: =Hypothèses!$C$4*$B6*Hypothèses!E$18*(1+Hypothèses!$C$13)^1 | R6: =Hypothèses!$C$4*$B6*Hypothèses!F$18*(1+Hypothèses!$C$13)^1 | S6: =Hypothèses!$C$4*$B6*Hypothèses!G$18*(1+Hypothèses!$C$13)^1 | T6: =Hypothèses!$C$4*$B6*Hypothèses!H$18*(1+Hypothèses!$C$13)^1 | U6: =Hypothèses!$C$4*$B6*Hypothèses!I$18*(1+Hypothèses!$C$13)^1 | V6: =Hypothèses!$C$4*$B6*Hypothèses!J$18*(1+Hypothèses!$C$13)^1 | ... Z6: =Hypothèses!$C$4*$B6*Hypothèses!N$18*(1+Hypothèses!$C$13)^1 | AA6: =Hypothèses!$C$4*$B6*Hypothèses!C$18*(1+Hypothèses!$C$13)^2 | AB6: =Hypothèses!$C$4*$B6*Hypothèses!D$18*(1+Hypothèses!$C$13)^2 | AC6: =Hypothèses!$C$4*$B6*Hypothèses!E$18*(1+Hypothèses!$C$13)^2 | AD6: =Hypothèses!$C$4*$B6*Hypothèses!F$18*(1+Hypothèses!$C$13)^2 | AE6: =Hypothèses!$C$4*$B6*Hypothèses!G$18*(1+Hypothèses!$C$13)^2 | AF6: =Hypothèses!$C$4*$B6*Hypothèses!H$18*(1+Hypothèses!$C$13)^2 | AG6: =Hypothèses!$C$4*$B6*Hypothèses!I$18*(1+Hypothèses!$C$13)^2 | AH6: =Hypothèses!$C$4*$B6*Hypothèses!J$18*(1+Hypothèses!$C$13)^2 | ... AL6: =Hypothèses!$C$4*$B6*Hypothèses!N$18*(1+Hypothèses!$C$13)^2 | AM6: =SUM(C6:N6) | AN6: =SUM(O6:Z6) | AO6: =SUM(AA6:AL6) | AP6: =SUM(AM6:AO6)
A7: Entretien chaudière / chauffe-eau (contrats) | B7: 0.2 | C7: =Hypothèses!$C$4*$B7*Hypothèses!C$18*(1+Hypothèses!$C$13)^0 | D7: =Hypothèses!$C$4*$B7*Hypothèses!D$18*(1+Hypothèses!$C$13)^0 | E7: =Hypothèses!$C$4*$B7*Hypothèses!E$18*(1+Hypothèses!$C$13)^0 | F7: =Hypothèses!$C$4*$B7*Hypothèses!F$18*(1+Hypothèses!$C$13)^0 | G7: =Hypothèses!$C$4*$B7*Hypothèses!G$18*(1+Hypothèses!$C$13)^0 | H7: =Hypothèses!$C$4*$B7*Hypothèses!H$18*(1+Hypothèses!$C$13)^0 | I7: =Hypothèses!$C$4*$B7*Hypothèses!I$18*(1+Hypothèses!$C$13)^0 | J7: =Hypothèses!$C$4*$B7*Hypothèses!J$18*(1+Hypothèses!$C$13)^0 | ... N7: =Hypothèses!$C$4*$B7*Hypothèses!N$18*(1+Hypothèses!$C$13)^0 | O7: =Hypothèses!$C$4*$B7*Hypothèses!C$18*(1+Hypothèses!$C$13)^1 | P7: =Hypothèses!$C$4*$B7*Hypothèses!D$18*(1+Hypothèses!$C$13)^1 | Q7: =Hypothèses!$C$4*$B7*Hypothèses!E$18*(1+Hypothèses!$C$13)^1 | R7: =Hypothèses!$C$4*$B7*Hypothèses!F$18*(1+Hypothèses!$C$13)^1 | S7: =Hypothèses!$C$4*$B7*Hypothèses!G$18*(1+Hypothèses!$C$13)^1 | T7: =Hypothèses!$C$4*$B7*Hypothèses!H$18*(1+Hypothèses!$C$13)^1 | U7: =Hypothèses!$C$4*$B7*Hypothèses!I$18*(1+Hypothèses!$C$13)^1 | V7: =Hypothèses!$C$4*$B7*Hypothèses!J$18*(1+Hypothèses!$C$13)^1 | ... Z7: =Hypothèses!$C$4*$B7*Hypothèses!N$18*(1+Hypothèses!$C$13)^1 | AA7: =Hypothèses!$C$4*$B7*Hypothèses!C$18*(1+Hypothèses!$C$13)^2 | AB7: =Hypothèses!$C$4*$B7*Hypothèses!D$18*(1+Hypothèses!$C$13)^2 | AC7: =Hypothèses!$C$4*$B7*Hypothèses!E$18*(1+Hypothèses!$C$13)^2 | AD7: =Hypothèses!$C$4*$B7*Hypothèses!F$18*(1+Hypothèses!$C$13)^2 | AE7: =Hypothèses!$C$4*$B7*Hypothèses!G$18*(1+Hypothèses!$C$13)^2 | AF7: =Hypothèses!$C$4*$B7*Hypothèses!H$18*(1+Hypothèses!$C$13)^2 | AG7: =Hypothèses!$C$4*$B7*Hypothèses!I$18*(1+Hypothèses!$C$13)^2 | AH7: =Hypothèses!$C$4*$B7*Hypothèses!J$18*(1+Hypothèses!$C$13)^2 | ... AL7: =Hypothèses!$C$4*$B7*Hypothèses!N$18*(1+Hypothèses!$C$13)^2 | AM7: =SUM(C7:N7) | AN7: =SUM(O7:Z7) | AO7: =SUM(AA7:AL7) | AP7: =SUM(AM7:AO7)
A8: Rénovation salle de bain / cuisine | B8: 0.25 | C8: =Hypothèses!$C$4*$B8*Hypothèses!C$18*(1+Hypothèses!$C$13)^0 | D8: =Hypothèses!$C$4*$B8*Hypothèses!D$18*(1+Hypothèses!$C$13)^0 | E8: =Hypothèses!$C$4*$B8*Hypothèses!E$18*(1+Hypothèses!$C$13)^0 | F8: =Hypothèses!$C$4*$B8*Hypothèses!F$18*(1+Hypothèses!$C$13)^0 | G8: =Hypothèses!$C$4*$B8*Hypothèses!G$18*(1+Hypothèses!$C$13)^0 | H8: =Hypothèses!$C$4*$B8*Hypothèses!H$18*(1+Hypothèses!$C$13)^0 | I8: =Hypothèses!$C$4*$B8*Hypothèses!I$18*(1+Hypothèses!$C$13)^0 | J8: =Hypothèses!$C$4*$B8*Hypothèses!J$18*(1+Hypothèses!$C$13)^0 | ... N8: =Hypothèses!$C$4*$B8*Hypothèses!N$18*(1+Hypothèses!$C$13)^0 | O8: =Hypothèses!$C$4*$B8*Hypothèses!C$18*(1+Hypothèses!$C$13)^1 | P8: =Hypothèses!$C$4*$B8*Hypothèses!D$18*(1+Hypothèses!$C$13)^1 | Q8: =Hypothèses!$C$4*$B8*Hypothèses!E$18*(1+Hypothèses!$C$13)^1 | R8: =Hypothèses!$C$4*$B8*Hypothèses!F$18*(1+Hypothèses!$C$13)^1 | S8: =Hypothèses!$C$4*$B8*Hypothèses!G$18*(1+Hypothèses!$C$13)^1 | T8: =Hypothèses!$C$4*$B8*Hypothèses!H$18*(1+Hypothèses!$C$13)^1 | U8: =Hypothèses!$C$4*$B8*Hypothèses!I$18*(1+Hypothèses!$C$13)^1 | V8: =Hypothèses!$C$4*$B8*Hypothèses!J$18*(1+Hypothèses!$C$13)^1 | ... Z8: =Hypothèses!$C$4*$B8*Hypothèses!N$18*(1+Hypothèses!$C$13)^1 | AA8: =Hypothèses!$C$4*$B8*Hypothèses!C$18*(1+Hypothèses!$C$13)^2 | AB8: =Hypothèses!$C$4*$B8*Hypothèses!D$18*(1+Hypothèses!$C$13)^2 | AC8: =Hypothèses!$C$4*$B8*Hypothèses!E$18*(1+Hypothèses!$C$13)^2 | AD8: =Hypothèses!$C$4*$B8*Hypothèses!F$18*(1+Hypothèses!$C$13)^2 | AE8: =Hypothèses!$C$4*$B8*Hypothèses!G$18*(1+Hypothèses!$C$13)^2 | AF8: =Hypothèses!$C$4*$B8*Hypothèses!H$18*(1+Hypothèses!$C$13)^2 | AG8: =Hypothèses!$C$4*$B8*Hypothèses!I$18*(1+Hypothèses!$C$13)^2 | AH8: =Hypothèses!$C$4*$B8*Hypothèses!J$18*(1+Hypothèses!$C$13)^2 | ... AL8: =Hypothèses!$C$4*$B8*Hypothèses!N$18*(1+Hypothèses!$C$13)^2 | AM8: =SUM(C8:N8) | AN8: =SUM(O8:Z8) | AO8: =SUM(AA8:AL8) | AP8: =SUM(AM8:AO8)
A9: TOTAL CA HT | C9: =SUM(C5:C8) | D9: =SUM(D5:D8) | E9: =SUM(E5:E8) | F9: =SUM(F5:F8) | G9: =SUM(G5:G8) | H9: =SUM(H5:H8) | I9: =SUM(I5:I8) | J9: =SUM(J5:J8) | ... AL9: =SUM(AL5:AL8) | AM9: =SUM(C9:N9) | AN9: =SUM(O9:Z9) | AO9: =SUM(AA9:AL9) | AP9: =SUM(AM9:AO9)
A10: Contrôle Σ % répartition (doit = 100%) | B10: =SUM(B5:B8)
A11: TVA collectée sur les ventes | C11: =C9*Hypothèses!$C$5 | D11: =D9*Hypothèses!$C$5 | E11: =E9*Hypothèses!$C$5 | F11: =F9*Hypothèses!$C$5 | G11: =G9*Hypothèses!$C$5 | H11: =H9*Hypothèses!$C$5 | I11: =I9*Hypothèses!$C$5 | J11: =J9*Hypothèses!$C$5 | ... AL11: =AL9*Hypothèses!$C$5 | AM11: =SUM(C11:N11) | AN11: =SUM(O11:Z11) | AO11: =SUM(AA11:AL11) | AP11: =SUM(AM11:AO11)
A12: CA TTC (encaissable) | C12: =C9+C11 | D12: =D9+D11 | E12: =E9+E11 | F12: =F9+F11 | G12: =G9+G11 | H12: =H9+H11 | I12: =I9+I11 | J12: =J9+J11 | ... AL12: =AL9+AL11 | AM12: =SUM(C12:N12) | AN12: =SUM(O12:Z12) | AO12: =SUM(AA12:AL12) | AP12: =SUM(AM12:AO12)

Sheet Dépenses détaillées
A1: Plombier — Dépenses détaillées (3 ans, mois par mois)
A2: Quantité de base × indice de saisonnalité × Prix (de base inflaté, ou simulé mois par mois pour les commodités) = Coût du mois.
G3: ANNÉE 1 | S3: ANNÉE 2 | AE3: ANNÉE 3
A4: Catégorie | B4: Poste | C4: Qté base/mois (A1) | D4: Unité | E4: Prix unitaire base (A1, €) | F4: Source prix | G4: Jan A1 | H4: Fév A1 | I4: Mar A1 | J4: Avr A1 | K4: Mai A1 | L4: Jui A1 | M4: Jui A1 | N4: Aoû A1 | O4: Sep A1 | P4: Oct A1 | Q4: Nov A1 | R4: Déc A1 | S4: Jan A2 | T4: Fév A2 | U4: Mar A2 | V4: Avr A2 | W4: Mai A2 | X4: Jui A2 | Y4: Jui A2 | Z4: Aoû A2 | AA4: Sep A2 | AB4: Oct A2 | AC4: Nov A2 | AD4: Déc A2 | AE4: Jan A3 | AF4: Fév A3 | AG4: Mar A3 | AH4: Avr A3 | AI4: Mai A3 | AJ4: Jui A3 | AK4: Jui A3 | AL4: Aoû A3 | AM4: Sep A3 | AN4: Oct A3 | AO4: Nov A3 | AP4: Déc A3 | AQ4: Total A1 | AR4: Total A2 | AS4: Total A3 | AT4: Total 3 ans
A5: Matériaux & fournitures | B5: Cuivre (tubes) — prix de marché simulé (€/unité) | D5: kg | E5: =AVERAGE(G5:AP5) | F5: API marché (COPPER, Alpha Vantage) — simulation calibrée, à remplacer par un fetch live | G5: 8.565 | H5: 9.225 | I5: 8.5328 | J5: 8.5818 | K5: 8.6815 | L5: 9.6026 | M5: 9.5718 | N5: 11.3789 | O5: 11.494 | P5: 13.5768 | Q5: 14.4639 | R5: 15.1211 | S5: 12.7036 | T5: 12.0246 | U5: 12.4596 | V5: 11.8673 | W5: 10.7991 | X5: 9.7164 | Y5: 10.3107 | Z5: 11.5228 | AA5: 12.3463 | AB5: 10.3148 | AC5: 10.5649 | AD5: 11.7796 | AE5: 9.8238 | AF5: 10.3005 | AG5: 10.3434 | AH5: 10.2344 | AI5: 11.5086 | AJ5: 11.0067 | AK5: 10.6141 | AL5: 12.5182 | AM5: 13.632 | AN5: 15.602 | AO5: 15.4438 | AP5: 15.3478
A6: Matériaux & fournitures | B6: ↳ Coût (Cuivre (tubes)) | C6: 15 | D6: kg | F6: Coût = Qté de base × saisonnalité × prix simulé ci-dessus | G6: =$C6*Hypothèses!C$17*G5 | H6: =$C6*Hypothèses!D$17*H5 | I6: =$C6*Hypothèses!E$17*I5 | J6: =$C6*Hypothèses!F$17*J5 | K6: =$C6*Hypothèses!G$17*K5 | L6: =$C6*Hypothèses!H$17*L5 | M6: =$C6*Hypothèses!I$17*M5 | N6: =$C6*Hypothèses!J$17*N5 | ... R6: =$C6*Hypothèses!N$17*R5 | S6: =$C6*Hypothèses!C$17*S5 | T6: =$C6*Hypothèses!D$17*T5 | U6: =$C6*Hypothèses!E$17*U5 | V6: =$C6*Hypothèses!F$17*V5 | W6: =$C6*Hypothèses!G$17*W5 | X6: =$C6*Hypothèses!H$17*X5 | Y6: =$C6*Hypothèses!I$17*Y5 | Z6: =$C6*Hypothèses!J$17*Z5 | ... AD6: =$C6*Hypothèses!N$17*AD5 | AE6: =$C6*Hypothèses!C$17*AE5 | AF6: =$C6*Hypothèses!D$17*AF5 | AG6: =$C6*Hypothèses!E$17*AG5 | AH6: =$C6*Hypothèses!F$17*AH5 | AI6: =$C6*Hypothèses!G$17*AI5 | AJ6: =$C6*Hypothèses!H$17*AJ5 | AK6: =$C6*Hypothèses!I$17*AK5 | AL6: =$C6*Hypothèses!J$17*AL5 | ... AP6: =$C6*Hypothèses!N$17*AP5 | AQ6: =SUM(G6:R6) | AR6: =SUM(S6:AD6) | AS6: =SUM(AE6:AP6) | AT6: =SUM(AQ6:AS6)
A7: Matériaux & fournitures | B7: Tube PER / multicouche | C7: 120 | D7: mètres | E7: 12 | F7: Sourcé — fourchette 9-40€/ml selon diamètre (Travaux.com) | G7: =$C7*Hypothèses!C$17*$E7*(1+Hypothèses!$C$14)^0 | H7: =$C7*Hypothèses!D$17*$E7*(1+Hypothèses!$C$14)^0 | I7: =$C7*Hypothèses!E$17*$E7*(1+Hypothèses!$C$14)^0 | J7: =$C7*Hypothèses!F$17*$E7*(1+Hypothèses!$C$14)^0 | K7: =$C7*Hypothèses!G$17*$E7*(1+Hypothèses!$C$14)^0 | L7: =$C7*Hypothèses!H$17*$E7*(1+Hypothèses!$C$14)^0 | M7: =$C7*Hypothèses!I$17*$E7*(1+Hypothèses!$C$14)^0 | N7: =$C7*Hypothèses!J$17*$E7*(1+Hypothèses!$C$14)^0 | ... R7: =$C7*Hypothèses!N$17*$E7*(1+Hypothèses!$C$14)^0 | S7: =$C7*Hypothèses!C$17*$E7*(1+Hypothèses!$C$14)^1 | T7: =$C7*Hypothèses!D$17*$E7*(1+Hypothèses!$C$14)^1 | U7: =$C7*Hypothèses!E$17*$E7*(1+Hypothèses!$C$14)^1 | V7: =$C7*Hypothèses!F$17*$E7*(1+Hypothèses!$C$14)^1 | W7: =$C7*Hypothèses!G$17*$E7*(1+Hypothèses!$C$14)^1 | X7: =$C7*Hypothèses!H$17*$E7*(1+Hypothèses!$C$14)^1 | Y7: =$C7*Hypothèses!I$17*$E7*(1+Hypothèses!$C$14)^1 | Z7: =$C7*Hypothèses!J$17*$E7*(1+Hypothèses!$C$14)^1 | ... AD7: =$C7*Hypothèses!N$17*$E7*(1+Hypothèses!$C$14)^1 | AE7: =$C7*Hypothèses!C$17*$E7*(1+Hypothèses!$C$14)^2 | AF7: =$C7*Hypothèses!D$17*$E7*(1+Hypothèses!$C$14)^2 | AG7: =$C7*Hypothèses!E$17*$E7*(1+Hypothèses!$C$14)^2 | AH7: =$C7*Hypothèses!F$17*$E7*(1+Hypothèses!$C$14)^2 | AI7: =$C7*Hypothèses!G$17*$E7*(1+Hypothèses!$C$14)^2 | AJ7: =$C7*Hypothèses!H$17*$E7*(1+Hypothèses!$C$14)^2 | AK7: =$C7*Hypothèses!I$17*$E7*(1+Hypothèses!$C$14)^2 | AL7: =$C7*Hypothèses!J$17*$E7*(1+Hypothèses!$C$14)^2 | ... AP7: =$C7*Hypothèses!N$17*$E7*(1+Hypothèses!$C$14)^2 | AQ7: =SUM(G7:R7) | AR7: =SUM(S7:AD7) | AS7: =SUM(AE7:AP7) | AT7: =SUM(AQ7:AS7)
A8: Matériaux & fournitures | B8: PVC évacuation | C8: 80 | D8: mètres | E8: 6 | F8: Estimé — négoce plomberie | G8: =$C8*Hypothèses!C$17*$E8*(1+Hypothèses!$C$14)^0 | H8: =$C8*Hypothèses!D$17*$E8*(1+Hypothèses!$C$14)^0 | I8: =$C8*Hypothèses!E$17*$E8*(1+Hypothèses!$C$14)^0 | J8: =$C8*Hypothèses!F$17*$E8*(1+Hypothèses!$C$14)^0 | K8: =$C8*Hypothèses!G$17*$E8*(1+Hypothèses!$C$14)^0 | L8: =$C8*Hypothèses!H$17*$E8*(1+Hypothèses!$C$14)^0 | M8: =$C8*Hypothèses!I$17*$E8*(1+Hypothèses!$C$14)^0 | N8: =$C8*Hypothèses!J$17*$E8*(1+Hypothèses!$C$14)^0 | ... R8: =$C8*Hypothèses!N$17*$E8*(1+Hypothèses!$C$14)^0 | S8: =$C8*Hypothèses!C$17*$E8*(1+Hypothèses!$C$14)^1 | T8: =$C8*Hypothèses!D$17*$E8*(1+Hypothèses!$C$14)^1 | U8: =$C8*Hypothèses!E$17*$E8*(1+Hypothèses!$C$14)^1 | V8: =$C8*Hypothèses!F$17*$E8*(1+Hypothèses!$C$14)^1 | W8: =$C8*Hypothèses!G$17*$E8*(1+Hypothèses!$C$14)^1 | X8: =$C8*Hypothèses!H$17*$E8*(1+Hypothèses!$C$14)^1 | Y8: =$C8*Hypothèses!I$17*$E8*(1+Hypothèses!$C$14)^1 | Z8: =$C8*Hypothèses!J$17*$E8*(1+Hypothèses!$C$14)^1 | ... AD8: =$C8*Hypothèses!N$17*$E8*(1+Hypothèses!$C$14)^1 | AE8: =$C8*Hypothèses!C$17*$E8*(1+Hypothèses!$C$14)^2 | AF8: =$C8*Hypothèses!D$17*$E8*(1+Hypothèses!$C$14)^2 | AG8: =$C8*Hypothèses!E$17*$E8*(1+Hypothèses!$C$14)^2 | AH8: =$C8*Hypothèses!F$17*$E8*(1+Hypothèses!$C$14)^2 | AI8: =$C8*Hypothèses!G$17*$E8*(1+Hypothèses!$C$14)^2 | AJ8: =$C8*Hypothèses!H$17*$E8*(1+Hypothèses!$C$14)^2 | AK8: =$C8*Hypothèses!I$17*$E8*(1+Hypothèses!$C$14)^2 | AL8: =$C8*Hypothèses!J$17*$E8*(1+Hypothèses!$C$14)^2 | ... AP8: =$C8*Hypothèses!N$17*$E8*(1+Hypothèses!$C$14)^2 | AQ8: =SUM(G8:R8) | AR8: =SUM(S8:AD8) | AS8: =SUM(AE8:AP8) | AT8: =SUM(AQ8:AS8)
A9: Matériaux & fournitures | B9: Raccords / fittings | C9: 300 | D9: unités | E9: 1.8 | F9: Estimé — négoce plomberie | G9: =$C9*Hypothèses!C$17*$E9*(1+Hypothèses!$C$14)^0 | H9: =$C9*Hypothèses!D$17*$E9*(1+Hypothèses!$C$14)^0 | I9: =$C9*Hypothèses!E$17*$E9*(1+Hypothèses!$C$14)^0 | J9: =$C9*Hypothèses!F$17*$E9*(1+Hypothèses!$C$14)^0 | K9: =$C9*Hypothèses!G$17*$E9*(1+Hypothèses!$C$14)^0 | L9: =$C9*Hypothèses!H$17*$E9*(1+Hypothèses!$C$14)^0 | M9: =$C9*Hypothèses!I$17*$E9*(1+Hypothèses!$C$14)^0 | N9: =$C9*Hypothèses!J$17*$E9*(1+Hypothèses!$C$14)^0 | ... R9: =$C9*Hypothèses!N$17*$E9*(1+Hypothèses!$C$14)^0 | S9: =$C9*Hypothèses!C$17*$E9*(1+Hypothèses!$C$14)^1 | T9: =$C9*Hypothèses!D$17*$E9*(1+Hypothèses!$C$14)^1 | U9: =$C9*Hypothèses!E$17*$E9*(1+Hypothèses!$C$14)^1 | V9: =$C9*Hypothèses!F$17*$E9*(1+Hypothèses!$C$14)^1 | W9: =$C9*Hypothèses!G$17*$E9*(1+Hypothèses!$C$14)^1 | X9: =$C9*Hypothèses!H$17*$E9*(1+Hypothèses!$C$14)^1 | Y9: =$C9*Hypothèses!I$17*$E9*(1+Hypothèses!$C$14)^1 | Z9: =$C9*Hypothèses!J$17*$E9*(1+Hypothèses!$C$14)^1 | ... AD9: =$C9*Hypothèses!N$17*$E9*(1+Hypothèses!$C$14)^1 | AE9: =$C9*Hypothèses!C$17*$E9*(1+Hypothèses!$C$14)^2 | AF9: =$C9*Hypothèses!D$17*$E9*(1+Hypothèses!$C$14)^2 | AG9: =$C9*Hypothèses!E$17*$E9*(1+Hypothèses!$C$14)^2 | AH9: =$C9*Hypothèses!F$17*$E9*(1+Hypothèses!$C$14)^2 | AI9: =$C9*Hypothèses!G$17*$E9*(1+Hypothèses!$C$14)^2 | AJ9: =$C9*Hypothèses!H$17*$E9*(1+Hypothèses!$C$14)^2 | AK9: =$C9*Hypothèses!I$17*$E9*(1+Hypothèses!$C$14)^2 | AL9: =$C9*Hypothèses!J$17*$E9*(1+Hypothèses!$C$14)^2 | ... AP9: =$C9*Hypothèses!N$17*$E9*(1+Hypothèses!$C$14)^2 | AQ9: =SUM(G9:R9) | AR9: =SUM(S9:AD9) | AS9: =SUM(AE9:AP9) | AT9: =SUM(AQ9:AS9)
A10: Matériaux & fournitures | B10: Robinetterie (mitigeurs, robinets) | C10: 12 | D10: unités | E10: 45 | F10: Estimé — négoce sanitaire | G10: =$C10*Hypothèses!C$17*$E10*(1+Hypothèses!$C$14)^0 | H10: =$C10*Hypothèses!D$17*$E10*(1+Hypothèses!$C$14)^0 | I10: =$C10*Hypothèses!E$17*$E10*(1+Hypothèses!$C$14)^0 | J10: =$C10*Hypothèses!F$17*$E10*(1+Hypothèses!$C$14)^0 | K10: =$C10*Hypothèses!G$17*$E10*(1+Hypothèses!$C$14)^0 | L10: =$C10*Hypothèses!H$17*$E10*(1+Hypothèses!$C$14)^0 | M10: =$C10*Hypothèses!I$17*$E10*(1+Hypothèses!$C$14)^0 | N10: =$C10*Hypothèses!J$17*$E10*(1+Hypothèses!$C$14)^0 | ... R10: =$C10*Hypothèses!N$17*$E10*(1+Hypothèses!$C$14)^0 | S10: =$C10*Hypothèses!C$17*$E10*(1+Hypothèses!$C$14)^1 | T10: =$C10*Hypothèses!D$17*$E10*(1+Hypothèses!$C$14)^1 | U10: =$C10*Hypothèses!E$17*$E10*(1+Hypothèses!$C$14)^1 | V10: =$C10*Hypothèses!F$17*$E10*(1+Hypothèses!$C$14)^1 | W10: =$C10*Hypothèses!G$17*$E10*(1+Hypothèses!$C$14)^1 | X10: =$C10*Hypothèses!H$17*$E10*(1+Hypothèses!$C$14)^1 | Y10: =$C10*Hypothèses!I$17*$E10*(1+Hypothèses!$C$14)^1 | Z10: =$C10*Hypothèses!J$17*$E10*(1+Hypothèses!$C$14)^1 | ... AD10: =$C10*Hypothèses!N$17*$E10*(1+Hypothèses!$C$14)^1 | AE10: =$C10*Hypothèses!C$17*$E10*(1+Hypothèses!$C$14)^2 | AF10: =$C10*Hypothèses!D$17*$E10*(1+Hypothèses!$C$14)^2 | AG10: =$C10*Hypothèses!E$17*$E10*(1+Hypothèses!$C$14)^2 | AH10: =$C10*Hypothèses!F$17*$E10*(1+Hypothèses!$C$14)^2 | AI10: =$C10*Hypothèses!G$17*$E10*(1+Hypothèses!$C$14)^2 | AJ10: =$C10*Hypothèses!H$17*$E10*(1+Hypothèses!$C$14)^2 | AK10: =$C10*Hypothèses!I$17*$E10*(1+Hypothèses!$C$14)^2 | AL10: =$C10*Hypothèses!J$17*$E10*(1+Hypothèses!$C$14)^2 | ... AP10: =$C10*Hypothèses!N$17*$E10*(1+Hypothèses!$C$14)^2 | AQ10: =SUM(G10:R10) | AR10: =SUM(S10:AD10) | AS10: =SUM(AE10:AP10) | AT10: =SUM(AQ10:AS10)
A11: Matériaux & fournitures | B11: Chauffe-eau / chaudières (équipements) | C11: 1.5 | D11: unités | E11: 550 | F11: Estimé — grossiste chauffage/sanitaire | G11: =$C11*Hypothèses!C$17*$E11*(1+Hypothèses!$C$14)^0 | H11: =$C11*Hypothèses!D$17*$E11*(1+Hypothèses!$C$14)^0 | I11: =$C11*Hypothèses!E$17*$E11*(1+Hypothèses!$C$14)^0 | J11: =$C11*Hypothèses!F$17*$E11*(1+Hypothèses!$C$14)^0 | K11: =$C11*Hypothèses!G$17*$E11*(1+Hypothèses!$C$14)^0 | L11: =$C11*Hypothèses!H$17*$E11*(1+Hypothèses!$C$14)^0 | M11: =$C11*Hypothèses!I$17*$E11*(1+Hypothèses!$C$14)^0 | N11: =$C11*Hypothèses!J$17*$E11*(1+Hypothèses!$C$14)^0 | ... R11: =$C11*Hypothèses!N$17*$E11*(1+Hypothèses!$C$14)^0 | S11: =$C11*Hypothèses!C$17*$E11*(1+Hypothèses!$C$14)^1 | T11: =$C11*Hypothèses!D$17*$E11*(1+Hypothèses!$C$14)^1 | U11: =$C11*Hypothèses!E$17*$E11*(1+Hypothèses!$C$14)^1 | V11: =$C11*Hypothèses!F$17*$E11*(1+Hypothèses!$C$14)^1 | W11: =$C11*Hypothèses!G$17*$E11*(1+Hypothèses!$C$14)^1 | X11: =$C11*Hypothèses!H$17*$E11*(1+Hypothèses!$C$14)^1 | Y11: =$C11*Hypothèses!I$17*$E11*(1+Hypothèses!$C$14)^1 | Z11: =$C11*Hypothèses!J$17*$E11*(1+Hypothèses!$C$14)^1 | ... AD11: =$C11*Hypothèses!N$17*$E11*(1+Hypothèses!$C$14)^1 | AE11: =$C11*Hypothèses!C$17*$E11*(1+Hypothèses!$C$14)^2 | AF11: =$C11*Hypothèses!D$17*$E11*(1+Hypothèses!$C$14)^2 | AG11: =$C11*Hypothèses!E$17*$E11*(1+Hypothèses!$C$14)^2 | AH11: =$C11*Hypothèses!F$17*$E11*(1+Hypothèses!$C$14)^2 | AI11: =$C11*Hypothèses!G$17*$E11*(1+Hypothèses!$C$14)^2 | AJ11: =$C11*Hypothèses!H$17*$E11*(1+Hypothèses!$C$14)^2 | AK11: =$C11*Hypothèses!I$17*$E11*(1+Hypothèses!$C$14)^2 | AL11: =$C11*Hypothèses!J$17*$E11*(1+Hypothèses!$C$14)^2 | ... AP11: =$C11*Hypothèses!N$17*$E11*(1+Hypothèses!$C$14)^2 | AQ11: =SUM(G11:R11) | AR11: =SUM(S11:AD11) | AS11: =SUM(AE11:AP11) | AT11: =SUM(AQ11:AS11)
A12: Matériaux & fournitures | B12: Joints & consommables (téflon, colle, joints) | C12: 1 | D12: forfait/mois | E12: 120 | F12: Estimé | G12: =$C12*Hypothèses!C$17*$E12*(1+Hypothèses!$C$14)^0 | H12: =$C12*Hypothèses!D$17*$E12*(1+Hypothèses!$C$14)^0 | I12: =$C12*Hypothèses!E$17*$E12*(1+Hypothèses!$C$14)^0 | J12: =$C12*Hypothèses!F$17*$E12*(1+Hypothèses!$C$14)^0 | K12: =$C12*Hypothèses!G$17*$E12*(1+Hypothèses!$C$14)^0 | L12: =$C12*Hypothèses!H$17*$E12*(1+Hypothèses!$C$14)^0 | M12: =$C12*Hypothèses!I$17*$E12*(1+Hypothèses!$C$14)^0 | N12: =$C12*Hypothèses!J$17*$E12*(1+Hypothèses!$C$14)^0 | ... R12: =$C12*Hypothèses!N$17*$E12*(1+Hypothèses!$C$14)^0 | S12: =$C12*Hypothèses!C$17*$E12*(1+Hypothèses!$C$14)^1 | T12: =$C12*Hypothèses!D$17*$E12*(1+Hypothèses!$C$14)^1 | U12: =$C12*Hypothèses!E$17*$E12*(1+Hypothèses!$C$14)^1 | V12: =$C12*Hypothèses!F$17*$E12*(1+Hypothèses!$C$14)^1 | W12: =$C12*Hypothèses!G$17*$E12*(1+Hypothèses!$C$14)^1 | X12: =$C12*Hypothèses!H$17*$E12*(1+Hypothèses!$C$14)^1 | Y12: =$C12*Hypothèses!I$17*$E12*(1+Hypothèses!$C$14)^1 | Z12: =$C12*Hypothèses!J$17*$E12*(1+Hypothèses!$C$14)^1 | ... AD12: =$C12*Hypothèses!N$17*$E12*(1+Hypothèses!$C$14)^1 | AE12: =$C12*Hypothèses!C$17*$E12*(1+Hypothèses!$C$14)^2 | AF12: =$C12*Hypothèses!D$17*$E12*(1+Hypothèses!$C$14)^2 | AG12: =$C12*Hypothèses!E$17*$E12*(1+Hypothèses!$C$14)^2 | AH12: =$C12*Hypothèses!F$17*$E12*(1+Hypothèses!$C$14)^2 | AI12: =$C12*Hypothèses!G$17*$E12*(1+Hypothèses!$C$14)^2 | AJ12: =$C12*Hypothèses!H$17*$E12*(1+Hypothèses!$C$14)^2 | AK12: =$C12*Hypothèses!I$17*$E12*(1+Hypothèses!$C$14)^2 | AL12: =$C12*Hypothèses!J$17*$E12*(1+Hypothèses!$C$14)^2 | ... AP12: =$C12*Hypothèses!N$17*$E12*(1+Hypothèses!$C$14)^2 | AQ12: =SUM(G12:R12) | AR12: =SUM(S12:AD12) | AS12: =SUM(AE12:AP12) | AT12: =SUM(AQ12:AS12)
A13: SOUS-TOTAL Matériaux & fournitures | G13: =G6+G7+G8+G9+G10+G11+G12 | H13: =H6+H7+H8+H9+H10+H11+H12 | I13: =I6+I7+I8+I9+I10+I11+I12 | J13: =J6+J7+J8+J9+J10+J11+J12 | K13: =K6+K7+K8+K9+K10+K11+K12 | L13: =L6+L7+L8+L9+L10+L11+L12 | M13: =M6+M7+M8+M9+M10+M11+M12 | N13: =N6+N7+N8+N9+N10+N11+N12 | ... AP13: =AP6+AP7+AP8+AP9+AP10+AP11+AP12 | AQ13: =SUM(G13:R13) | AR13: =SUM(S13:AD13) | AS13: =SUM(AE13:AP13) | AT13: =SUM(AQ13:AS13)
A14: Carburant & véhicule | B14: Carburant véhicule utilitaire — prix de marché simulé (€/unité) | D14: litres | E14: =AVERAGE(G14:AP14) | F14: API marché (proxy WTI/BRENT, Alpha Vantage) — simulation calibrée | G14: 1.8802 | H14: 1.8526 | I14: 1.7362 | J14: 1.6999 | K14: 1.713 | L14: 1.7419 | M14: 1.6455 | N14: 1.718 | O14: 1.7354 | P14: 1.6443 | Q14: 1.6942 | R14: 1.6874 | S14: 1.6765 | T14: 1.6587 | U14: 1.671 | V14: 1.725 | W14: 1.8821 | X14: 1.8616 | Y14: 1.6546 | Z14: 1.5912 | AA14: 1.6824 | AB14: 1.656 | AC14: 1.7116 | AD14: 1.6493 | AE14: 1.5988 | AF14: 1.4286 | AG14: 1.3407 | AH14: 1.4243 | AI14: 1.4218 | AJ14: 1.3875 | AK14: 1.3937 | AL14: 1.3407 | AM14: 1.3279 | AN14: 1.3873 | AO14: 1.3464 | AP14: 1.5375
A15: Carburant & véhicule | B15: ↳ Coût (Carburant véhicule utilitaire) | C15: 320 | D15: litres | F15: Coût = Qté de base × saisonnalité × prix simulé ci-dessus | G15: =$C15*Hypothèses!C$17*G14 | H15: =$C15*Hypothèses!D$17*H14 | I15: =$C15*Hypothèses!E$17*I14 | J15: =$C15*Hypothèses!F$17*J14 | K15: =$C15*Hypothèses!G$17*K14 | L15: =$C15*Hypothèses!H$17*L14 | M15: =$C15*Hypothèses!I$17*M14 | N15: =$C15*Hypothèses!J$17*N14 | ... R15: =$C15*Hypothèses!N$17*R14 | S15: =$C15*Hypothèses!C$17*S14 | T15: =$C15*Hypothèses!D$17*T14 | U15: =$C15*Hypothèses!E$17*U14 | V15: =$C15*Hypothèses!F$17*V14 | W15: =$C15*Hypothèses!G$17*W14 | X15: =$C15*Hypothèses!H$17*X14 | Y15: =$C15*Hypothèses!I$17*Y14 | Z15: =$C15*Hypothèses!J$17*Z14 | ... AD15: =$C15*Hypothèses!N$17*AD14 | AE15: =$C15*Hypothèses!C$17*AE14 | AF15: =$C15*Hypothèses!D$17*AF14 | AG15: =$C15*Hypothèses!E$17*AG14 | AH15: =$C15*Hypothèses!F$17*AH14 | AI15: =$C15*Hypothèses!G$17*AI14 | AJ15: =$C15*Hypothèses!H$17*AJ14 | AK15: =$C15*Hypothèses!I$17*AK14 | AL15: =$C15*Hypothèses!J$17*AL14 | ... AP15: =$C15*Hypothèses!N$17*AP14 | AQ15: =SUM(G15:R15) | AR15: =SUM(S15:AD15) | AS15: =SUM(AE15:AP15) | AT15: =SUM(AQ15:AS15)
A16: Carburant & véhicule | B16: Entretien véhicule | C16: 1 | D16: forfait/mois | E16: 110 | F16: Estimé | G16: =$C16*Hypothèses!C$17*$E16*(1+Hypothèses!$C$14)^0 | H16: =$C16*Hypothèses!D$17*$E16*(1+Hypothèses!$C$14)^0 | I16: =$C16*Hypothèses!E$17*$E16*(1+Hypothèses!$C$14)^0 | J16: =$C16*Hypothèses!F$17*$E16*(1+Hypothèses!$C$14)^0 | K16: =$C16*Hypothèses!G$17*$E16*(1+Hypothèses!$C$14)^0 | L16: =$C16*Hypothèses!H$17*$E16*(1+Hypothèses!$C$14)^0 | M16: =$C16*Hypothèses!I$17*$E16*(1+Hypothèses!$C$14)^0 | N16: =$C16*Hypothèses!J$17*$E16*(1+Hypothèses!$C$14)^0 | ... R16: =$C16*Hypothèses!N$17*$E16*(1+Hypothèses!$C$14)^0 | S16: =$C16*Hypothèses!C$17*$E16*(1+Hypothèses!$C$14)^1 | T16: =$C16*Hypothèses!D$17*$E16*(1+Hypothèses!$C$14)^1 | U16: =$C16*Hypothèses!E$17*$E16*(1+Hypothèses!$C$14)^1 | V16: =$C16*Hypothèses!F$17*$E16*(1+Hypothèses!$C$14)^1 | W16: =$C16*Hypothèses!G$17*$E16*(1+Hypothèses!$C$14)^1 | X16: =$C16*Hypothèses!H$17*$E16*(1+Hypothèses!$C$14)^1 | Y16: =$C16*Hypothèses!I$17*$E16*(1+Hypothèses!$C$14)^1 | Z16: =$C16*Hypothèses!J$17*$E16*(1+Hypothèses!$C$14)^1 | ... AD16: =$C16*Hypothèses!N$17*$E16*(1+Hypothèses!$C$14)^1 | AE16: =$C16*Hypothèses!C$17*$E16*(1+Hypothèses!$C$14)^2 | AF16: =$C16*Hypothèses!D$17*$E16*(1+Hypothèses!$C$14)^2 | AG16: =$C16*Hypothèses!E$17*$E16*(1+Hypothèses!$C$14)^2 | AH16: =$C16*Hypothèses!F$17*$E16*(1+Hypothèses!$C$14)^2 | AI16: =$C16*Hypothèses!G$17*$E16*(1+Hypothèses!$C$14)^2 | AJ16: =$C16*Hypothèses!H$17*$E16*(1+Hypothèses!$C$14)^2 | AK16: =$C16*Hypothèses!I$17*$E16*(1+Hypothèses!$C$14)^2 | AL16: =$C16*Hypothèses!J$17*$E16*(1+Hypothèses!$C$14)^2 | ... AP16: =$C16*Hypothèses!N$17*$E16*(1+Hypothèses!$C$14)^2 | AQ16: =SUM(G16:R16) | AR16: =SUM(S16:AD16) | AS16: =SUM(AE16:AP16) | AT16: =SUM(AQ16:AS16)
A17: SOUS-TOTAL Carburant & véhicule | G17: =G15+G16 | H17: =H15+H16 | I17: =I15+I16 | J17: =J15+J16 | K17: =K15+K16 | L17: =L15+L16 | M17: =M15+M16 | N17: =N15+N16 | ... AP17: =AP15+AP16 | AQ17: =SUM(G17:R17) | AR17: =SUM(S17:AD17) | AS17: =SUM(AE17:AP17) | AT17: =SUM(AQ17:AS17)
A18: Personnel | B18: Rémunération nette du dirigeant (plombier, TNS) | C18: 1 | D18: forfait/mois | E18: 3400 | F18: Estimé | G18: =$C18*$E18*(1+Hypothèses!$C$14)^0 | H18: =$C18*$E18*(1+Hypothèses!$C$14)^0 | I18: =$C18*$E18*(1+Hypothèses!$C$14)^0 | J18: =$C18*$E18*(1+Hypothèses!$C$14)^0 | K18: =$C18*$E18*(1+Hypothèses!$C$14)^0 | L18: =$C18*$E18*(1+Hypothèses!$C$14)^0 | M18: =$C18*$E18*(1+Hypothèses!$C$14)^0 | N18: =$C18*$E18*(1+Hypothèses!$C$14)^0 | ... R18: =$C18*$E18*(1+Hypothèses!$C$14)^0 | S18: =$C18*$E18*(1+Hypothèses!$C$14)^1 | T18: =$C18*$E18*(1+Hypothèses!$C$14)^1 | U18: =$C18*$E18*(1+Hypothèses!$C$14)^1 | V18: =$C18*$E18*(1+Hypothèses!$C$14)^1 | W18: =$C18*$E18*(1+Hypothèses!$C$14)^1 | X18: =$C18*$E18*(1+Hypothèses!$C$14)^1 | Y18: =$C18*$E18*(1+Hypothèses!$C$14)^1 | Z18: =$C18*$E18*(1+Hypothèses!$C$14)^1 | ... AD18: =$C18*$E18*(1+Hypothèses!$C$14)^1 | AE18: =$C18*$E18*(1+Hypothèses!$C$14)^2 | AF18: =$C18*$E18*(1+Hypothèses!$C$14)^2 | AG18: =$C18*$E18*(1+Hypothèses!$C$14)^2 | AH18: =$C18*$E18*(1+Hypothèses!$C$14)^2 | AI18: =$C18*$E18*(1+Hypothèses!$C$14)^2 | AJ18: =$C18*$E18*(1+Hypothèses!$C$14)^2 | AK18: =$C18*$E18*(1+Hypothèses!$C$14)^2 | AL18: =$C18*$E18*(1+Hypothèses!$C$14)^2 | ... AP18: =$C18*$E18*(1+Hypothèses!$C$14)^2 | AQ18: =SUM(G18:R18) | AR18: =SUM(S18:AD18) | AS18: =SUM(AE18:AP18) | AT18: =SUM(AQ18:AS18)
A19: Personnel | B19: Salaires & charges — 1 aide/apprenti | C19: 1 | D19: forfait/mois | E19: 2600 | F19: Estimé — grille bâtiment | G19: =$C19*$E19*(1+Hypothèses!$C$14)^0 | H19: =$C19*$E19*(1+Hypothèses!$C$14)^0 | I19: =$C19*$E19*(1+Hypothèses!$C$14)^0 | J19: =$C19*$E19*(1+Hypothèses!$C$14)^0 | K19: =$C19*$E19*(1+Hypothèses!$C$14)^0 | L19: =$C19*$E19*(1+Hypothèses!$C$14)^0 | M19: =$C19*$E19*(1+Hypothèses!$C$14)^0 | N19: =$C19*$E19*(1+Hypothèses!$C$14)^0 | ... R19: =$C19*$E19*(1+Hypothèses!$C$14)^0 | S19: =$C19*$E19*(1+Hypothèses!$C$14)^1 | T19: =$C19*$E19*(1+Hypothèses!$C$14)^1 | U19: =$C19*$E19*(1+Hypothèses!$C$14)^1 | V19: =$C19*$E19*(1+Hypothèses!$C$14)^1 | W19: =$C19*$E19*(1+Hypothèses!$C$14)^1 | X19: =$C19*$E19*(1+Hypothèses!$C$14)^1 | Y19: =$C19*$E19*(1+Hypothèses!$C$14)^1 | Z19: =$C19*$E19*(1+Hypothèses!$C$14)^1 | ... AD19: =$C19*$E19*(1+Hypothèses!$C$14)^1 | AE19: =$C19*$E19*(1+Hypothèses!$C$14)^2 | AF19: =$C19*$E19*(1+Hypothèses!$C$14)^2 | AG19: =$C19*$E19*(1+Hypothèses!$C$14)^2 | AH19: =$C19*$E19*(1+Hypothèses!$C$14)^2 | AI19: =$C19*$E19*(1+Hypothèses!$C$14)^2 | AJ19: =$C19*$E19*(1+Hypothèses!$C$14)^2 | AK19: =$C19*$E19*(1+Hypothèses!$C$14)^2 | AL19: =$C19*$E19*(1+Hypothèses!$C$14)^2 | ... AP19: =$C19*$E19*(1+Hypothèses!$C$14)^2 | AQ19: =SUM(G19:R19) | AR19: =SUM(S19:AD19) | AS19: =SUM(AE19:AP19) | AT19: =SUM(AQ19:AS19)
A20: SOUS-TOTAL Personnel | G20: =G18+G19 | H20: =H18+H19 | I20: =I18+I19 | J20: =J18+J19 | K20: =K18+K19 | L20: =L18+L19 | M20: =M18+M19 | N20: =N18+N19 | ... AP20: =AP18+AP19 | AQ20: =SUM(G20:R20) | AR20: =SUM(S20:AD20) | AS20: =SUM(AE20:AP20) | AT20: =SUM(AQ20:AS20)
A21: Charges sociales dirigeant | B21: Cotisations URSSAF (TNS) du dirigeant — lissé mensuel (versées par trimestre, cf. Hypothèses C8) | C21: 1 | D21: forfait/mois (moy.) | E21: 666.67 | F21: Calculé — Hypothèses!C8 (cotisation trimestrielle) ÷ 3 | G21: =$C21*$E21*(1+Hypothèses!$C$14)^0 | H21: =$C21*$E21*(1+Hypothèses!$C$14)^0 | I21: =$C21*$E21*(1+Hypothèses!$C$14)^0 | J21: =$C21*$E21*(1+Hypothèses!$C$14)^0 | K21: =$C21*$E21*(1+Hypothèses!$C$14)^0 | L21: =$C21*$E21*(1+Hypothèses!$C$14)^0 | M21: =$C21*$E21*(1+Hypothèses!$C$14)^0 | N21: =$C21*$E21*(1+Hypothèses!$C$14)^0 | ... R21: =$C21*$E21*(1+Hypothèses!$C$14)^0 | S21: =$C21*$E21*(1+Hypothèses!$C$14)^1 | T21: =$C21*$E21*(1+Hypothèses!$C$14)^1 | U21: =$C21*$E21*(1+Hypothèses!$C$14)^1 | V21: =$C21*$E21*(1+Hypothèses!$C$14)^1 | W21: =$C21*$E21*(1+Hypothèses!$C$14)^1 | X21: =$C21*$E21*(1+Hypothèses!$C$14)^1 | Y21: =$C21*$E21*(1+Hypothèses!$C$14)^1 | Z21: =$C21*$E21*(1+Hypothèses!$C$14)^1 | ... AD21: =$C21*$E21*(1+Hypothèses!$C$14)^1 | AE21: =$C21*$E21*(1+Hypothèses!$C$14)^2 | AF21: =$C21*$E21*(1+Hypothèses!$C$14)^2 | AG21: =$C21*$E21*(1+Hypothèses!$C$14)^2 | AH21: =$C21*$E21*(1+Hypothèses!$C$14)^2 | AI21: =$C21*$E21*(1+Hypothèses!$C$14)^2 | AJ21: =$C21*$E21*(1+Hypothèses!$C$14)^2 | AK21: =$C21*$E21*(1+Hypothèses!$C$14)^2 | AL21: =$C21*$E21*(1+Hypothèses!$C$14)^2 | ... AP21: =$C21*$E21*(1+Hypothèses!$C$14)^2 | AQ21: =SUM(G21:R21) | AR21: =SUM(S21:AD21) | AS21: =SUM(AE21:AP21) | AT21: =SUM(AQ21:AS21)
A22: SOUS-TOTAL Charges sociales dirigeant | G22: =G21 | H22: =H21 | I22: =I21 | J22: =J21 | K22: =K21 | L22: =L21 | M22: =M21 | N22: =N21 | ... AP22: =AP21 | AQ22: =SUM(G22:R22) | AR22: =SUM(S22:AD22) | AS22: =SUM(AE22:AP22) | AT22: =SUM(AQ22:AS22)
A23: Énergie | B23: Électricité (local / atelier) — prix de marché simulé (€/unité) | D23: kWh | E23: =AVERAGE(G23:AP23) | F23: API/marché (Tarif Bleu Pro EDF — simulation calibrée, à actualiser via SDES) | G23: 0.1646 | H23: 0.166 | I23: 0.1689 | J23: 0.1768 | K23: 0.1789 | L23: 0.1837 | M23: 0.1856 | N23: 0.1884 | O23: 0.1876 | P23: 0.1872 | Q23: 0.1826 | R23: 0.1765 | S23: 0.1755 | T23: 0.175 | U23: 0.1728 | V23: 0.1749 | W23: 0.1794 | X23: 0.1826 | Y23: 0.1815 | Z23: 0.188 | AA23: 0.1886 | AB23: 0.1913 | AC23: 0.1936 | AD23: 0.1911 | AE23: 0.1897 | AF23: 0.1848 | AG23: 0.1838 | AH23: 0.1801 | AI23: 0.1803 | AJ23: 0.1816 | AK23: 0.186 | AL23: 0.1823 | AM23: 0.1827 | AN23: 0.1779 | AO23: 0.1776 | AP23: 0.1818
A24: Énergie | B24: ↳ Coût (Électricité (local / atelier)) | C24: 1050 | D24: kWh | F24: Coût = Qté de base × saisonnalité × prix simulé ci-dessus | G24: =$C24*Hypothèses!C$17*G23 | H24: =$C24*Hypothèses!D$17*H23 | I24: =$C24*Hypothèses!E$17*I23 | J24: =$C24*Hypothèses!F$17*J23 | K24: =$C24*Hypothèses!G$17*K23 | L24: =$C24*Hypothèses!H$17*L23 | M24: =$C24*Hypothèses!I$17*M23 | N24: =$C24*Hypothèses!J$17*N23 | ... R24: =$C24*Hypothèses!N$17*R23 | S24: =$C24*Hypothèses!C$17*S23 | T24: =$C24*Hypothèses!D$17*T23 | U24: =$C24*Hypothèses!E$17*U23 | V24: =$C24*Hypothèses!F$17*V23 | W24: =$C24*Hypothèses!G$17*W23 | X24: =$C24*Hypothèses!H$17*X23 | Y24: =$C24*Hypothèses!I$17*Y23 | Z24: =$C24*Hypothèses!J$17*Z23 | ... AD24: =$C24*Hypothèses!N$17*AD23 | AE24: =$C24*Hypothèses!C$17*AE23 | AF24: =$C24*Hypothèses!D$17*AF23 | AG24: =$C24*Hypothèses!E$17*AG23 | AH24: =$C24*Hypothèses!F$17*AH23 | AI24: =$C24*Hypothèses!G$17*AI23 | AJ24: =$C24*Hypothèses!H$17*AJ23 | AK24: =$C24*Hypothèses!I$17*AK23 | AL24: =$C24*Hypothèses!J$17*AL23 | ... AP24: =$C24*Hypothèses!N$17*AP23 | AQ24: =SUM(G24:R24) | AR24: =SUM(S24:AD24) | AS24: =SUM(AE24:AP24) | AT24: =SUM(AQ24:AS24)
A25: SOUS-TOTAL Énergie | G25: =G24 | H25: =H24 | I25: =I24 | J25: =J24 | K25: =K24 | L25: =L24 | M25: =M24 | N25: =N24 | ... AP25: =AP24 | AQ25: =SUM(G25:R25) | AR25: =SUM(S25:AD25) | AS25: =SUM(AE25:AP25) | AT25: =SUM(AQ25:AS25)
A26: Charges fixes | B26: Loyer local / dépôt | C26: 1 | D26: forfait/mois | E26: 900 | F26: Estimé | G26: =$C26*$E26*(1+Hypothèses!$C$14)^0 | H26: =$C26*$E26*(1+Hypothèses!$C$14)^0 | I26: =$C26*$E26*(1+Hypothèses!$C$14)^0 | J26: =$C26*$E26*(1+Hypothèses!$C$14)^0 | K26: =$C26*$E26*(1+Hypothèses!$C$14)^0 | L26: =$C26*$E26*(1+Hypothèses!$C$14)^0 | M26: =$C26*$E26*(1+Hypothèses!$C$14)^0 | N26: =$C26*$E26*(1+Hypothèses!$C$14)^0 | ... R26: =$C26*$E26*(1+Hypothèses!$C$14)^0 | S26: =$C26*$E26*(1+Hypothèses!$C$14)^1 | T26: =$C26*$E26*(1+Hypothèses!$C$14)^1 | U26: =$C26*$E26*(1+Hypothèses!$C$14)^1 | V26: =$C26*$E26*(1+Hypothèses!$C$14)^1 | W26: =$C26*$E26*(1+Hypothèses!$C$14)^1 | X26: =$C26*$E26*(1+Hypothèses!$C$14)^1 | Y26: =$C26*$E26*(1+Hypothèses!$C$14)^1 | Z26: =$C26*$E26*(1+Hypothèses!$C$14)^1 | ... AD26: =$C26*$E26*(1+Hypothèses!$C$14)^1 | AE26: =$C26*$E26*(1+Hypothèses!$C$14)^2 | AF26: =$C26*$E26*(1+Hypothèses!$C$14)^2 | AG26: =$C26*$E26*(1+Hypothèses!$C$14)^2 | AH26: =$C26*$E26*(1+Hypothèses!$C$14)^2 | AI26: =$C26*$E26*(1+Hypothèses!$C$14)^2 | AJ26: =$C26*$E26*(1+Hypothèses!$C$14)^2 | AK26: =$C26*$E26*(1+Hypothèses!$C$14)^2 | AL26: =$C26*$E26*(1+Hypothèses!$C$14)^2 | ... AP26: =$C26*$E26*(1+Hypothèses!$C$14)^2 | AQ26: =SUM(G26:R26) | AR26: =SUM(S26:AD26) | AS26: =SUM(AE26:AP26) | AT26: =SUM(AQ26:AS26)
A27: Charges fixes | B27: Assurance décennale | C27: 1 | D27: forfait/mois | E27: 550 | F27: Sourcé — exemple de prime ≈2 440€/an, ajusté à la baisse (artisan expérimenté, réduction -25%) | G27: =$C27*$E27*(1+Hypothèses!$C$14)^0 | H27: =$C27*$E27*(1+Hypothèses!$C$14)^0 | I27: =$C27*$E27*(1+Hypothèses!$C$14)^0 | J27: =$C27*$E27*(1+Hypothèses!$C$14)^0 | K27: =$C27*$E27*(1+Hypothèses!$C$14)^0 | L27: =$C27*$E27*(1+Hypothèses!$C$14)^0 | M27: =$C27*$E27*(1+Hypothèses!$C$14)^0 | N27: =$C27*$E27*(1+Hypothèses!$C$14)^0 | ... R27: =$C27*$E27*(1+Hypothèses!$C$14)^0 | S27: =$C27*$E27*(1+Hypothèses!$C$14)^1 | T27: =$C27*$E27*(1+Hypothèses!$C$14)^1 | U27: =$C27*$E27*(1+Hypothèses!$C$14)^1 | V27: =$C27*$E27*(1+Hypothèses!$C$14)^1 | W27: =$C27*$E27*(1+Hypothèses!$C$14)^1 | X27: =$C27*$E27*(1+Hypothèses!$C$14)^1 | Y27: =$C27*$E27*(1+Hypothèses!$C$14)^1 | Z27: =$C27*$E27*(1+Hypothèses!$C$14)^1 | ... AD27: =$C27*$E27*(1+Hypothèses!$C$14)^1 | AE27: =$C27*$E27*(1+Hypothèses!$C$14)^2 | AF27: =$C27*$E27*(1+Hypothèses!$C$14)^2 | AG27: =$C27*$E27*(1+Hypothèses!$C$14)^2 | AH27: =$C27*$E27*(1+Hypothèses!$C$14)^2 | AI27: =$C27*$E27*(1+Hypothèses!$C$14)^2 | AJ27: =$C27*$E27*(1+Hypothèses!$C$14)^2 | AK27: =$C27*$E27*(1+Hypothèses!$C$14)^2 | AL27: =$C27*$E27*(1+Hypothèses!$C$14)^2 | ... AP27: =$C27*$E27*(1+Hypothèses!$C$14)^2 | AQ27: =SUM(G27:R27) | AR27: =SUM(S27:AD27) | AS27: =SUM(AE27:AP27) | AT27: =SUM(AQ27:AS27)
A28: Charges fixes | B28: Assurance RC professionnelle & véhicule | C28: 1 | D28: forfait/mois | E28: 320 | F28: Estimé | G28: =$C28*$E28*(1+Hypothèses!$C$14)^0 | H28: =$C28*$E28*(1+Hypothèses!$C$14)^0 | I28: =$C28*$E28*(1+Hypothèses!$C$14)^0 | J28: =$C28*$E28*(1+Hypothèses!$C$14)^0 | K28: =$C28*$E28*(1+Hypothèses!$C$14)^0 | L28: =$C28*$E28*(1+Hypothèses!$C$14)^0 | M28: =$C28*$E28*(1+Hypothèses!$C$14)^0 | N28: =$C28*$E28*(1+Hypothèses!$C$14)^0 | ... R28: =$C28*$E28*(1+Hypothèses!$C$14)^0 | S28: =$C28*$E28*(1+Hypothèses!$C$14)^1 | T28: =$C28*$E28*(1+Hypothèses!$C$14)^1 | U28: =$C28*$E28*(1+Hypothèses!$C$14)^1 | V28: =$C28*$E28*(1+Hypothèses!$C$14)^1 | W28: =$C28*$E28*(1+Hypothèses!$C$14)^1 | X28: =$C28*$E28*(1+Hypothèses!$C$14)^1 | Y28: =$C28*$E28*(1+Hypothèses!$C$14)^1 | Z28: =$C28*$E28*(1+Hypothèses!$C$14)^1 | ... AD28: =$C28*$E28*(1+Hypothèses!$C$14)^1 | AE28: =$C28*$E28*(1+Hypothèses!$C$14)^2 | AF28: =$C28*$E28*(1+Hypothèses!$C$14)^2 | AG28: =$C28*$E28*(1+Hypothèses!$C$14)^2 | AH28: =$C28*$E28*(1+Hypothèses!$C$14)^2 | AI28: =$C28*$E28*(1+Hypothèses!$C$14)^2 | AJ28: =$C28*$E28*(1+Hypothèses!$C$14)^2 | AK28: =$C28*$E28*(1+Hypothèses!$C$14)^2 | AL28: =$C28*$E28*(1+Hypothèses!$C$14)^2 | ... AP28: =$C28*$E28*(1+Hypothèses!$C$14)^2 | AQ28: =SUM(G28:R28) | AR28: =SUM(S28:AD28) | AS28: =SUM(AE28:AP28) | AT28: =SUM(AQ28:AS28)
A29: Charges fixes | B29: Honoraires comptable | C29: 1 | D29: forfait/mois | E29: 450 | F29: Estimé | G29: =$C29*$E29*(1+Hypothèses!$C$14)^0 | H29: =$C29*$E29*(1+Hypothèses!$C$14)^0 | I29: =$C29*$E29*(1+Hypothèses!$C$14)^0 | J29: =$C29*$E29*(1+Hypothèses!$C$14)^0 | K29: =$C29*$E29*(1+Hypothèses!$C$14)^0 | L29: =$C29*$E29*(1+Hypothèses!$C$14)^0 | M29: =$C29*$E29*(1+Hypothèses!$C$14)^0 | N29: =$C29*$E29*(1+Hypothèses!$C$14)^0 | ... R29: =$C29*$E29*(1+Hypothèses!$C$14)^0 | S29: =$C29*$E29*(1+Hypothèses!$C$14)^1 | T29: =$C29*$E29*(1+Hypothèses!$C$14)^1 | U29: =$C29*$E29*(1+Hypothèses!$C$14)^1 | V29: =$C29*$E29*(1+Hypothèses!$C$14)^1 | W29: =$C29*$E29*(1+Hypothèses!$C$14)^1 | X29: =$C29*$E29*(1+Hypothèses!$C$14)^1 | Y29: =$C29*$E29*(1+Hypothèses!$C$14)^1 | Z29: =$C29*$E29*(1+Hypothèses!$C$14)^1 | ... AD29: =$C29*$E29*(1+Hypothèses!$C$14)^1 | AE29: =$C29*$E29*(1+Hypothèses!$C$14)^2 | AF29: =$C29*$E29*(1+Hypothèses!$C$14)^2 | AG29: =$C29*$E29*(1+Hypothèses!$C$14)^2 | AH29: =$C29*$E29*(1+Hypothèses!$C$14)^2 | AI29: =$C29*$E29*(1+Hypothèses!$C$14)^2 | AJ29: =$C29*$E29*(1+Hypothèses!$C$14)^2 | AK29: =$C29*$E29*(1+Hypothèses!$C$14)^2 | AL29: =$C29*$E29*(1+Hypothèses!$C$14)^2 | ... AP29: =$C29*$E29*(1+Hypothèses!$C$14)^2 | AQ29: =SUM(G29:R29) | AR29: =SUM(S29:AD29) | AS29: =SUM(AE29:AP29) | AT29: =SUM(AQ29:AS29)
A30: Charges fixes | B30: Téléphonie / logiciel devis-facturation | C30: 1 | D30: forfait/mois | E30: 90 | F30: Estimé | G30: =$C30*$E30*(1+Hypothèses!$C$14)^0 | H30: =$C30*$E30*(1+Hypothèses!$C$14)^0 | I30: =$C30*$E30*(1+Hypothèses!$C$14)^0 | J30: =$C30*$E30*(1+Hypothèses!$C$14)^0 | K30: =$C30*$E30*(1+Hypothèses!$C$14)^0 | L30: =$C30*$E30*(1+Hypothèses!$C$14)^0 | M30: =$C30*$E30*(1+Hypothèses!$C$14)^0 | N30: =$C30*$E30*(1+Hypothèses!$C$14)^0 | ... R30: =$C30*$E30*(1+Hypothèses!$C$14)^0 | S30: =$C30*$E30*(1+Hypothèses!$C$14)^1 | T30: =$C30*$E30*(1+Hypothèses!$C$14)^1 | U30: =$C30*$E30*(1+Hypothèses!$C$14)^1 | V30: =$C30*$E30*(1+Hypothèses!$C$14)^1 | W30: =$C30*$E30*(1+Hypothèses!$C$14)^1 | X30: =$C30*$E30*(1+Hypothèses!$C$14)^1 | Y30: =$C30*$E30*(1+Hypothèses!$C$14)^1 | Z30: =$C30*$E30*(1+Hypothèses!$C$14)^1 | ... AD30: =$C30*$E30*(1+Hypothèses!$C$14)^1 | AE30: =$C30*$E30*(1+Hypothèses!$C$14)^2 | AF30: =$C30*$E30*(1+Hypothèses!$C$14)^2 | AG30: =$C30*$E30*(1+Hypothèses!$C$14)^2 | AH30: =$C30*$E30*(1+Hypothèses!$C$14)^2 | AI30: =$C30*$E30*(1+Hypothèses!$C$14)^2 | AJ30: =$C30*$E30*(1+Hypothèses!$C$14)^2 | AK30: =$C30*$E30*(1+Hypothèses!$C$14)^2 | AL30: =$C30*$E30*(1+Hypothèses!$C$14)^2 | ... AP30: =$C30*$E30*(1+Hypothèses!$C$14)^2 | AQ30: =SUM(G30:R30) | AR30: =SUM(S30:AD30) | AS30: =SUM(AE30:AP30) | AT30: =SUM(AQ30:AS30)
A31: Charges fixes | B31: Fournitures bureau & équipements de protection (EPI) | C31: 1 | D31: forfait/mois | E31: 120 | F31: Estimé | G31: =$C31*$E31*(1+Hypothèses!$C$14)^0 | H31: =$C31*$E31*(1+Hypothèses!$C$14)^0 | I31: =$C31*$E31*(1+Hypothèses!$C$14)^0 | J31: =$C31*$E31*(1+Hypothèses!$C$14)^0 | K31: =$C31*$E31*(1+Hypothèses!$C$14)^0 | L31: =$C31*$E31*(1+Hypothèses!$C$14)^0 | M31: =$C31*$E31*(1+Hypothèses!$C$14)^0 | N31: =$C31*$E31*(1+Hypothèses!$C$14)^0 | ... R31: =$C31*$E31*(1+Hypothèses!$C$14)^0 | S31: =$C31*$E31*(1+Hypothèses!$C$14)^1 | T31: =$C31*$E31*(1+Hypothèses!$C$14)^1 | U31: =$C31*$E31*(1+Hypothèses!$C$14)^1 | V31: =$C31*$E31*(1+Hypothèses!$C$14)^1 | W31: =$C31*$E31*(1+Hypothèses!$C$14)^1 | X31: =$C31*$E31*(1+Hypothèses!$C$14)^1 | Y31: =$C31*$E31*(1+Hypothèses!$C$14)^1 | Z31: =$C31*$E31*(1+Hypothèses!$C$14)^1 | ... AD31: =$C31*$E31*(1+Hypothèses!$C$14)^1 | AE31: =$C31*$E31*(1+Hypothèses!$C$14)^2 | AF31: =$C31*$E31*(1+Hypothèses!$C$14)^2 | AG31: =$C31*$E31*(1+Hypothèses!$C$14)^2 | AH31: =$C31*$E31*(1+Hypothèses!$C$14)^2 | AI31: =$C31*$E31*(1+Hypothèses!$C$14)^2 | AJ31: =$C31*$E31*(1+Hypothèses!$C$14)^2 | AK31: =$C31*$E31*(1+Hypothèses!$C$14)^2 | AL31: =$C31*$E31*(1+Hypothèses!$C$14)^2 | ... AP31: =$C31*$E31*(1+Hypothèses!$C$14)^2 | AQ31: =SUM(G31:R31) | AR31: =SUM(S31:AD31) | AS31: =SUM(AE31:AP31) | AT31: =SUM(AQ31:AS31)
A32: Charges fixes | B32: Frais bancaires | C32: 1 | D32: forfait/mois | E32: 100 | F32: Estimé | G32: =$C32*$E32*(1+Hypothèses!$C$14)^0 | H32: =$C32*$E32*(1+Hypothèses!$C$14)^0 | I32: =$C32*$E32*(1+Hypothèses!$C$14)^0 | J32: =$C32*$E32*(1+Hypothèses!$C$14)^0 | K32: =$C32*$E32*(1+Hypothèses!$C$14)^0 | L32: =$C32*$E32*(1+Hypothèses!$C$14)^0 | M32: =$C32*$E32*(1+Hypothèses!$C$14)^0 | N32: =$C32*$E32*(1+Hypothèses!$C$14)^0 | ... R32: =$C32*$E32*(1+Hypothèses!$C$14)^0 | S32: =$C32*$E32*(1+Hypothèses!$C$14)^1 | T32: =$C32*$E32*(1+Hypothèses!$C$14)^1 | U32: =$C32*$E32*(1+Hypothèses!$C$14)^1 | V32: =$C32*$E32*(1+Hypothèses!$C$14)^1 | W32: =$C32*$E32*(1+Hypothèses!$C$14)^1 | X32: =$C32*$E32*(1+Hypothèses!$C$14)^1 | Y32: =$C32*$E32*(1+Hypothèses!$C$14)^1 | Z32: =$C32*$E32*(1+Hypothèses!$C$14)^1 | ... AD32: =$C32*$E32*(1+Hypothèses!$C$14)^1 | AE32: =$C32*$E32*(1+Hypothèses!$C$14)^2 | AF32: =$C32*$E32*(1+Hypothèses!$C$14)^2 | AG32: =$C32*$E32*(1+Hypothèses!$C$14)^2 | AH32: =$C32*$E32*(1+Hypothèses!$C$14)^2 | AI32: =$C32*$E32*(1+Hypothèses!$C$14)^2 | AJ32: =$C32*$E32*(1+Hypothèses!$C$14)^2 | AK32: =$C32*$E32*(1+Hypothèses!$C$14)^2 | AL32: =$C32*$E32*(1+Hypothèses!$C$14)^2 | ... AP32: =$C32*$E32*(1+Hypothèses!$C$14)^2 | AQ32: =SUM(G32:R32) | AR32: =SUM(S32:AD32) | AS32: =SUM(AE32:AP32) | AT32: =SUM(AQ32:AS32)
A33: Charges fixes | B33: Impôts & taxes (CFE et autres) | C33: 1 | D33: forfait/mois | E33: 280 | F33: Estimé | G33: =$C33*$E33*(1+Hypothèses!$C$14)^0 | H33: =$C33*$E33*(1+Hypothèses!$C$14)^0 | I33: =$C33*$E33*(1+Hypothèses!$C$14)^0 | J33: =$C33*$E33*(1+Hypothèses!$C$14)^0 | K33: =$C33*$E33*(1+Hypothèses!$C$14)^0 | L33: =$C33*$E33*(1+Hypothèses!$C$14)^0 | M33: =$C33*$E33*(1+Hypothèses!$C$14)^0 | N33: =$C33*$E33*(1+Hypothèses!$C$14)^0 | ... R33: =$C33*$E33*(1+Hypothèses!$C$14)^0 | S33: =$C33*$E33*(1+Hypothèses!$C$14)^1 | T33: =$C33*$E33*(1+Hypothèses!$C$14)^1 | U33: =$C33*$E33*(1+Hypothèses!$C$14)^1 | V33: =$C33*$E33*(1+Hypothèses!$C$14)^1 | W33: =$C33*$E33*(1+Hypothèses!$C$14)^1 | X33: =$C33*$E33*(1+Hypothèses!$C$14)^1 | Y33: =$C33*$E33*(1+Hypothèses!$C$14)^1 | Z33: =$C33*$E33*(1+Hypothèses!$C$14)^1 | ... AD33: =$C33*$E33*(1+Hypothèses!$C$14)^1 | AE33: =$C33*$E33*(1+Hypothèses!$C$14)^2 | AF33: =$C33*$E33*(1+Hypothèses!$C$14)^2 | AG33: =$C33*$E33*(1+Hypothèses!$C$14)^2 | AH33: =$C33*$E33*(1+Hypothèses!$C$14)^2 | AI33: =$C33*$E33*(1+Hypothèses!$C$14)^2 | AJ33: =$C33*$E33*(1+Hypothèses!$C$14)^2 | AK33: =$C33*$E33*(1+Hypothèses!$C$14)^2 | AL33: =$C33*$E33*(1+Hypothèses!$C$14)^2 | ... AP33: =$C33*$E33*(1+Hypothèses!$C$14)^2 | AQ33: =SUM(G33:R33) | AR33: =SUM(S33:AD33) | AS33: =SUM(AE33:AP33) | AT33: =SUM(AQ33:AS33)
A34: SOUS-TOTAL Charges fixes | G34: =G26+G27+G28+G29+G30+G31+G32+G33 | H34: =H26+H27+H28+H29+H30+H31+H32+H33 | I34: =I26+I27+I28+I29+I30+I31+I32+I33 | J34: =J26+J27+J28+J29+J30+J31+J32+J33 | K34: =K26+K27+K28+K29+K30+K31+K32+K33 | L34: =L26+L27+L28+L29+L30+L31+L32+L33 | M34: =M26+M27+M28+M29+M30+M31+M32+M33 | N34: =N26+N27+N28+N29+N30+N31+N32+N33 | ... AP34: =AP26+AP27+AP28+AP29+AP30+AP31+AP32+AP33 | AQ34: =SUM(G34:R34) | AR34: =SUM(S34:AD34) | AS34: =SUM(AE34:AP34) | AT34: =SUM(AQ34:AS34)
A35: TOTAL GÉNÉRAL DÉPENSES | G35: =G13+G17+G20+G22+G25+G34 | H35: =H13+H17+H20+H22+H25+H34 | I35: =I13+I17+I20+I22+I25+I34 | J35: =J13+J17+J20+J22+J25+J34 | K35: =K13+K17+K20+K22+K25+K34 | L35: =L13+L17+L20+L22+L25+L34 | M35: =M13+M17+M20+M22+M25+M34 | N35: =N13+N17+N20+N22+N25+N34 | ... AP35: =AP13+AP17+AP20+AP22+AP25+AP34 | AQ35: =SUM(G35:R35) | AR35: =SUM(S35:AD35) | AS35: =SUM(AE35:AP35) | AT35: =SUM(AQ35:AS35)
A36: Total dépenses Année 1 / CA Année 1 (contrôle benchmark) | AQ36: =AQ35/AM9
A37: Marge brute « matériaux » seuls (CA − matériaux & fournitures) / CA — Année 1 | AQ37: =(Hypothèses!$C$4-AQ13)/Hypothèses!$C$4

Sheet Plan de trésorerie
A1: Plombier — Plan de trésorerie mensuel (3 ans)
A2: Trésorerie début + encaissements − décaissements = trésorerie fin. Chaque poste reprend le détail mensuel de l'onglet Dépenses détaillées.
C3: ANNÉE 1 | O3: ANNÉE 2 | AA3: ANNÉE 3
A4: Mois | C4: Jan A1 | D4: Fév A1 | E4: Mar A1 | F4: Avr A1 | G4: Mai A1 | H4: Jui A1 | I4: Jui A1 | J4: Aoû A1 | K4: Sep A1 | L4: Oct A1 | M4: Nov A1 | N4: Déc A1 | O4: Jan A2 | P4: Fév A2 | Q4: Mar A2 | R4: Avr A2 | S4: Mai A2 | T4: Jui A2 | U4: Jui A2 | V4: Aoû A2 | W4: Sep A2 | X4: Oct A2 | Y4: Nov A2 | Z4: Déc A2 | AA4: Jan A3 | AB4: Fév A3 | AC4: Mar A3 | AD4: Avr A3 | AE4: Mai A3 | AF4: Jui A3 | AG4: Jui A3 | AH4: Aoû A3 | AI4: Sep A3 | AJ4: Oct A3 | AK4: Nov A3 | AL4: Déc A3 | AM4: Total A1 | AN4: Total A2 | AO4: Total A3 | AP4: Total 3 ans
A5: Trésorerie en début de mois | C5: =Hypothèses!$C$7 | D5: =C19 | E5: =D19 | F5: =E19 | G5: =F19 | H5: =G19 | I5: =H19 | J5: =I19 | K5: =J19 | ... AL5: =AK19
A6: ENCAISSEMENTS
A7: Encaissements clients (CA TTC, paiement à la prestation) | C7: =Revenus!C12*Hypothèses!$C$10 | D7: =Revenus!D12*Hypothèses!$C$10 | E7: =Revenus!E12*Hypothèses!$C$10 | F7: =Revenus!F12*Hypothèses!$C$10 | G7: =Revenus!G12*Hypothèses!$C$10 | H7: =Revenus!H12*Hypothèses!$C$10 | I7: =Revenus!I12*Hypothèses!$C$10 | J7: =Revenus!J12*Hypothèses!$C$10 | ... AL7: =Revenus!AL12*Hypothèses!$C$10 | AM7: =SUM(C7:N7) | AN7: =SUM(O7:Z7) | AO7: =SUM(AA7:AL7) | AP7: =SUM(AM7:AO7)
A8: TOTAL ENCAISSEMENTS | C8: =C7 | D8: =D7 | E8: =E7 | F8: =F7 | G8: =G7 | H8: =H7 | I8: =I7 | J8: =J7 | ... AL8: =AL7 | AM8: =SUM(C8:N8) | AN8: =SUM(O8:Z8) | AO8: =SUM(AA8:AL8) | AP8: =SUM(AM8:AO8)
A9: DÉCAISSEMENTS
A10: Matériaux & fournitures (détail mensuel — onglet Dépenses) | C10: ='Dépenses détaillées'!G13 | D10: ='Dépenses détaillées'!H13 | E10: ='Dépenses détaillées'!I13 | F10: ='Dépenses détaillées'!J13 | G10: ='Dépenses détaillées'!K13 | H10: ='Dépenses détaillées'!L13 | I10: ='Dépenses détaillées'!M13 | J10: ='Dépenses détaillées'!N13 | ... AL10: ='Dépenses détaillées'!AP13 | AM10: =SUM(C10:N10) | AN10: =SUM(O10:Z10) | AO10: =SUM(AA10:AL10) | AP10: =SUM(AM10:AO10)
A11: Carburant & véhicule (détail mensuel — onglet Dépenses) | C11: ='Dépenses détaillées'!G17 | D11: ='Dépenses détaillées'!H17 | E11: ='Dépenses détaillées'!I17 | F11: ='Dépenses détaillées'!J17 | G11: ='Dépenses détaillées'!K17 | H11: ='Dépenses détaillées'!L17 | I11: ='Dépenses détaillées'!M17 | J11: ='Dépenses détaillées'!N17 | ... AL11: ='Dépenses détaillées'!AP17 | AM11: =SUM(C11:N11) | AN11: =SUM(O11:Z11) | AO11: =SUM(AA11:AL11) | AP11: =SUM(AM11:AO11)
A12: Personnel (salaires & charges) | C12: ='Dépenses détaillées'!G20 | D12: ='Dépenses détaillées'!H20 | E12: ='Dépenses détaillées'!I20 | F12: ='Dépenses détaillées'!J20 | G12: ='Dépenses détaillées'!K20 | H12: ='Dépenses détaillées'!L20 | I12: ='Dépenses détaillées'!M20 | J12: ='Dépenses détaillées'!N20 | ... AL12: ='Dépenses détaillées'!AP20 | AM12: =SUM(C12:N12) | AN12: =SUM(O12:Z12) | AO12: =SUM(AA12:AL12) | AP12: =SUM(AM12:AO12)
A13: Cotisations sociales dirigeant (versement trimestriel, inflaté) | C13: 0 | D13: 0 | E13: =Hypothèses!$C$8*(1+Hypothèses!$C$14)^0 | F13: 0 | G13: 0 | H13: =Hypothèses!$C$8*(1+Hypothèses!$C$14)^0 | I13: 0 | J13: 0 | K13: =Hypothèses!$C$8*(1+Hypothèses!$C$14)^0 | L13: 0 | M13: 0 | N13: =Hypothèses!$C$8*(1+Hypothèses!$C$14)^0 | O13: 0 | P13: 0 | Q13: =Hypothèses!$C$8*(1+Hypothèses!$C$14)^1 | R13: 0 | S13: 0 | T13: =Hypothèses!$C$8*(1+Hypothèses!$C$14)^1 | U13: 0 | V13: 0 | W13: =Hypothèses!$C$8*(1+Hypothèses!$C$14)^1 | X13: 0 | Y13: 0 | Z13: =Hypothèses!$C$8*(1+Hypothèses!$C$14)^1 | AA13: 0 | AB13: 0 | AC13: =Hypothèses!$C$8*(1+Hypothèses!$C$14)^2 | AD13: 0 | AE13: 0 | AF13: =Hypothèses!$C$8*(1+Hypothèses!$C$14)^2 | AG13: 0 | AH13: 0 | AI13: =Hypothèses!$C$8*(1+Hypothèses!$C$14)^2 | AJ13: 0 | AK13: 0 | AL13: =Hypothèses!$C$8*(1+Hypothèses!$C$14)^2 | AM13: =SUM(C13:N13) | AN13: =SUM(O13:Z13) | AO13: =SUM(AA13:AL13) | AP13: =SUM(AM13:AO13)
A14: Charges fixes & énergie local (loyer, assurances, comptable...) | C14: =('Dépenses détaillées'!G34+'Dépenses détaillées'!G25) | D14: =('Dépenses détaillées'!H34+'Dépenses détaillées'!H25) | E14: =('Dépenses détaillées'!I34+'Dépenses détaillées'!I25) | F14: =('Dépenses détaillées'!J34+'Dépenses détaillées'!J25) | G14: =('Dépenses détaillées'!K34+'Dépenses détaillées'!K25) | H14: =('Dépenses détaillées'!L34+'Dépenses détaillées'!L25) | I14: =('Dépenses détaillées'!M34+'Dépenses détaillées'!M25) | J14: =('Dépenses détaillées'!N34+'Dépenses détaillées'!N25) | ... AL14: =('Dépenses détaillées'!AP34+'Dépenses détaillées'!AP25) | AM14: =SUM(C14:N14) | AN14: =SUM(O14:Z14) | AO14: =SUM(AA14:AL14) | AP14: =SUM(AM14:AO14)
A15: TVA nette versée (versement trimestriel) | C15: 0 | D15: 0 | E15: =MAX(0,SUM(C23:E23)) | F15: 0 | G15: 0 | H15: =MAX(0,SUM(F23:H23)) | I15: 0 | J15: 0 | K15: =MAX(0,SUM(I23:K23)) | L15: 0 | M15: 0 | N15: =MAX(0,SUM(L23:N23)) | O15: 0 | P15: 0 | Q15: =MAX(0,SUM(O23:Q23)) | R15: 0 | S15: 0 | T15: =MAX(0,SUM(R23:T23)) | U15: 0 | V15: 0 | W15: =MAX(0,SUM(U23:W23)) | X15: 0 | Y15: 0 | Z15: =MAX(0,SUM(X23:Z23)) | AA15: 0 | AB15: 0 | AC15: =MAX(0,SUM(AA23:AC23)) | AD15: 0 | AE15: 0 | AF15: =MAX(0,SUM(AD23:AF23)) | AG15: 0 | AH15: 0 | AI15: =MAX(0,SUM(AG23:AI23)) | AJ15: 0 | AK15: 0 | AL15: =MAX(0,SUM(AJ23:AL23)) | AM15: =SUM(C15:N15) | AN15: =SUM(O15:Z15) | AO15: =SUM(AA15:AL15) | AP15: =SUM(AM15:AO15)
A16: Remboursement emprunt véhicule/outillage (mensualité fixe) | C16: =Hypothèses!$C$9 | D16: =Hypothèses!$C$9 | E16: =Hypothèses!$C$9 | F16: =Hypothèses!$C$9 | G16: =Hypothèses!$C$9 | H16: =Hypothèses!$C$9 | I16: =Hypothèses!$C$9 | J16: =Hypothèses!$C$9 | ... AL16: =Hypothèses!$C$9 | AM16: =SUM(C16:N16) | AN16: =SUM(O16:Z16) | AO16: =SUM(AA16:AL16) | AP16: =SUM(AM16:AO16)
A17: TOTAL DÉCAISSEMENTS | C17: =SUM(C10:C16) | D17: =SUM(D10:D16) | E17: =SUM(E10:E16) | F17: =SUM(F10:F16) | G17: =SUM(G10:G16) | H17: =SUM(H10:H16) | I17: =SUM(I10:I16) | J17: =SUM(J10:J16) | ... AL17: =SUM(AL10:AL16) | AM17: =SUM(C17:N17) | AN17: =SUM(O17:Z17) | AO17: =SUM(AA17:AL17) | AP17: =SUM(AM17:AO17)
A18: Variation de trésorerie du mois | C18: =C8-C17 | D18: =D8-D17 | E18: =E8-E17 | F18: =F8-F17 | G18: =G8-G17 | H18: =H8-H17 | I18: =I8-I17 | J18: =J8-J17 | ... AL18: =AL8-AL17 | AM18: =SUM(C18:N18) | AN18: =SUM(O18:Z18) | AO18: =SUM(AA18:AL18) | AP18: =SUM(AM18:AO18)
A19: TRÉSORERIE EN FIN DE MOIS | C19: =C5+C18 | D19: =D5+D18 | E19: =E5+E18 | F19: =F5+F18 | G19: =G5+G18 | H19: =H5+H18 | I19: =I5+I18 | J19: =J5+J18 | ... AL19: =AL5+AL18 | AM19: =N19 | AN19: =Z19 | AO19: =AL19 | AP19: =AL19
A21: Mémo — TVA collectée du mois | C21: =Revenus!C11 | D21: =Revenus!D11 | E21: =Revenus!E11 | F21: =Revenus!F11 | G21: =Revenus!G11 | H21: =Revenus!H11 | I21: =Revenus!I11 | J21: =Revenus!J11 | ... AL21: =Revenus!AL11
A22: Mémo — TVA déductible du mois (estimée) | C22: =(C10+C11+C14)*Hypothèses!$C$6 | D22: =(D10+D11+D14)*Hypothèses!$C$6 | E22: =(E10+E11+E14)*Hypothèses!$C$6 | F22: =(F10+F11+F14)*Hypothèses!$C$6 | G22: =(G10+G11+G14)*Hypothèses!$C$6 | H22: =(H10+H11+H14)*Hypothèses!$C$6 | I22: =(I10+I11+I14)*Hypothèses!$C$6 | J22: =(J10+J11+J14)*Hypothèses!$C$6 | ... AL22: =(AL10+AL11+AL14)*Hypothèses!$C$6
A23: Mémo — TVA nette du mois | C23: =C21-C22 | D23: =D21-D22 | E23: =E21-E22 | F23: =F21-F22 | G23: =G21-G22 | H23: =H21-H22 | I23: =I21-I22 | J23: =J21-J22 | ... AL23: =AL21-AL22

Sheet Benchmarks & sources
A1: Plombier — Benchmarks & sources
A2: Ratios sectoriels retenus pour construire les hypothèses du modèle
A3: Indicateur | B3: Valeur retenue | C3: Source | D3: Commentaire
A4: Chiffre d'affaires annuel moyen (plomberie & chauffage) | B4: ≈ 200 k€ (fourchette 150-250k€ retenue) | C4: Cerfrance — Chiffres clés plomberie & chauffage 2023-2024 | D4: CA exemple cité : 409 929 € pour une structure plus grande ; modèle calibré pour une TPE, en Année 1.
A5: Marge nette réelle (exemple cité) | B5: 13,4 % (résultat courant / CA, cas réel 409 929 € CA) | C5: Modèles de Business Plan — Devenir plombier | D5: Modèle Année 1 ≈13,6%, très proche de cet exemple réel ; se resserre ensuite (inflation 3%/an > croissance CA 2,5%/an).
A6: Marge brute (au sens « cost of sales » BTP, matériaux + main d'œuvre dédiée) | B6: 30 à 50 % | C6: Modèles de Business Plan | D6: Modèle Année 1 : (CA − matériaux − personnel direct)/CA ≈ 39,5%, dans la fourchette.
A7: Marge brute « matériaux seuls » | B7: Non documentée séparément | C7: — | D7: Modèle : (CA − matériaux & fournitures)/CA ≈ 75% Année 1 — cohérent avec un métier où la main d'œuvre, pas la matière, est le principal poste de coût.
A8: Poids matériaux dans le CA | B8: 20 à 35 % selon type d'intervention | C8: Cerfrance | D8: Modèle retient ≈24,5% en Année 1.
A9: Poids approvisionnement + personnel dans les charges | B9: 85 à 87 % des charges d'exploitation | C9: Cerfrance | D9: Cohérent avec la structure du modèle.
A10: Tarif horaire plombier | B10: 40 à 90 € HT/h | C10: Travaux.com / guides de prix 2026 | D10: Référence indirecte pour vérifier la cohérence du chiffrage de la main d'œuvre.
A11: Prix tube cuivre | B11: 11 à 50 €/ml (selon diamètre) | C11: Travaux.com — guide des prix tuyauterie 2026 | D11: Le cuivre brut (kg) utilise une simulation mensuelle calibrée (placeholder API COPPER).
A12: Prix tube PER / multicouche | B12: 9 à 40 €/ml selon diamètre | C12: Travaux.com / Tafsquare | D12: Prix en dur retenu : 12€/ml Année 1 (inflaté ensuite).
A13: Assurance décennale — exemple de prime | B13: ≈ 2 440 €/an, réductions jusqu'à -25% pour artisans expérimentés | C13: Aric-assurances | D13: Modèle retient ≈6 600€/an Année 1 avec réduction artisan expérimenté.
A14: Délai de paiement | B14: Paiement majoritairement à la prestation (cash/CB/chèque) | C14: Hypothèse métier (clientèle particuliers) | D14: Modèle : 100% encaissé le mois même — à ajuster si forte clientèle professionnelle/syndics (délais 30j).
... A18: Simulation des prix de marché mensuels | B18: Marche aléatoire calibrée (drift + volatilité) autour des niveaux sourcés | C18: Méthodologie interne (fonction simulate_price_series) | D18: Remplace une inflation lissée par une vraie variation mois par mois sur cuivre, carburant, électricité.
